unidump/__init__.py
unidump/__main__.py
unidump/cli.py
unidump/env.py
unidump/output.py
unidump/locale/de/LC_MESSAGES/unidump.mo
unidump-1.1.4.dist-info/LICENSE.md
unidump-1.1.4.dist-info/METADATA
unidump-1.1.4.dist-info/WHEEL
unidump-1.1.4.dist-info/entry_points.txt
unidump-1.1.4.dist-info/top_level.txt
unidump-1.1.4.dist-info/RECORD
