Metadata-Version: 2.1
Name: unidump
Version: 1.1.4
Summary: hexdump for your Unicode data
Home-page: https://github.com/Codepoints/unidump
Author: Manuel Strehl
Author-email: boldewyn@gmail.com
License: MIT
Keywords: unicode hexdump debugging codepoint utility
Platform: UNKNOWN
Classifier: Development Status :: 5 - Production/Stable
Classifier: Intended Audience :: Developers
Classifier: Topic :: Software Development :: Debuggers
Classifier: Topic :: Software Development :: Internationalization
Classifier: Topic :: Software Development :: Testing
Classifier: Topic :: Text Processing :: General
Classifier: Topic :: Utilities
Classifier: License :: OSI Approved :: MIT License
Classifier: Programming Language :: Python :: 3
Classifier: Programming Language :: Python :: 3.3
Classifier: Programming Language :: Python :: 3.4
Classifier: Programming Language :: Python :: 3.5
License-File: LICENSE.md
